gocardless
test
