Metadata-Version: 1.1
Name: gocardless
Version: 0.5.2
Summary: The Python client library for the GoCardless API
Home-page: https://gocardless.com/docs/python/merchant_client_guide
Author: GoCardless
Author-email: developers@{nospam}gocardless.com
License: MIT
Platform: any
Classifier: Development Status :: 4 - Beta
Classifier: Intended Audience :: Developers
Classifier: License :: OSI Approved :: MIT License
Classifier: Operating System :: OS Independent
Classifier: Programming Language :: Python
Classifier: Topic :: Software Development :: Libraries :: Python Modules
